spakky/data/__init__.py
spakky/data/external/__init__.py
spakky/data/external/error.py
spakky/data/external/proxy.py
spakky/data/persistency/__init__.py
spakky/data/persistency/error.py
spakky/data/persistency/repository.py
spakky/data/persistency/transaction.py
spakky/data/stereotype/__init__.py
spakky/data/stereotype/repository.py
spakky_data-5.0.1.dist-info/WHEEL
spakky_data-5.0.1.dist-info/METADATA
spakky_data-5.0.1.dist-info/RECORD
