Metadata-Version: 2.3
Name: spakky-data
Version: 5.0.1
Summary: Data access layer for Spakky Framework (Repository implementations, ORM integration)
Author: Spakky
Author-email: Spakky <sejong418@icloud.com>
Requires-Dist: spakky-domain>=5.0.1
Requires-Python: >=3.11
